LICENSE.md
MANIFEST.in
README.md
pyproject.toml
setup.py
pysaliency/__init__.py
pysaliency/baseline_utils.py
pysaliency/dataset_config.py
pysaliency/datasets.py
pysaliency/filter_datasets.py
pysaliency/metric_optimization.py
pysaliency/metric_optimization_tf.py
pysaliency/metric_optimization_torch.py
pysaliency/metrics.py
pysaliency/models.py
pysaliency/numba_utils.py
pysaliency/plotting.py
pysaliency/precomputed_models.py
pysaliency/quilt.py
pysaliency/roc.py
pysaliency/roc_cython.c
pysaliency/roc_cython.pyx
pysaliency/saliency_map_conversion.py
pysaliency/saliency_map_conversion_theano.py
pysaliency/saliency_map_conversion_torch.py
pysaliency/saliency_map_models.py
pysaliency/sampling_models.py
pysaliency/tf_utils.py
pysaliency/theano_utils.py
pysaliency/torch_datasets.py
pysaliency/torch_utils.py
pysaliency/utils.py
pysaliency.egg-info/PKG-INFO
pysaliency.egg-info/SOURCES.txt
pysaliency.egg-info/dependency_links.txt
pysaliency.egg-info/requires.txt
pysaliency.egg-info/top_level.txt
pysaliency/external_datasets/__init__.py
pysaliency/external_datasets/cat2000.py
pysaliency/external_datasets/coco_freeview.py
pysaliency/external_datasets/coco_search18.py
pysaliency/external_datasets/dut_omrom.py
pysaliency/external_datasets/figrim.py
pysaliency/external_datasets/isun.py
pysaliency/external_datasets/koehler.py
pysaliency/external_datasets/mit.py
pysaliency/external_datasets/nusef.py
pysaliency/external_datasets/osie.py
pysaliency/external_datasets/pascal_s.py
pysaliency/external_datasets/salicon.py
pysaliency/external_datasets/toronto.py
pysaliency/external_datasets/utils.py
pysaliency/external_datasets/scripts/extract_fixations.m
pysaliency/external_datasets/scripts/load_cat2000.m
pysaliency/external_models/__init__.py
pysaliency/external_models/deepgaze.py
pysaliency/external_models/matlab_models.py
pysaliency/external_models/models.py
pysaliency/external_models/utils.py
pysaliency/external_models/scripts/AIM_wrapper.m
pysaliency/external_models/scripts/ContextAwareSaliency_wrapper.m
pysaliency/external_models/scripts/CovSal_wrapper.m
pysaliency/external_models/scripts/IttiKoch_wrapper.m
