Metadata-Version: 2.1
Name: pysaliency
Version: 0.2.22
Summary: python library to develop, evaluate and benchmark saliency models
Home-page: https://github.com/matthiask/pysaliency
Author: Matthias Kümmerer
Author-email: matthias.kuemmerer@bethgelab.org
License: MIT
Classifier: Development Status :: 3 - Alpha
Classifier: Intended Audience :: Developers
Classifier: Intended Audience :: Science/Research
Classifier: License :: OSI Approved :: MIT License
Classifier: Programming Language :: Python :: 3
Classifier: Programming Language :: Python :: 3.6
Classifier: Topic :: Scientific/Engineering
License-File: LICENSE.md
Requires-Dist: boltons
Requires-Dist: deprecation
Requires-Dist: dill
Requires-Dist: imageio
Requires-Dist: natsort
Requires-Dist: numba
Requires-Dist: numpy
Requires-Dist: piexif
Requires-Dist: requests
Requires-Dist: schema
Requires-Dist: scipy
Requires-Dist: setuptools
Requires-Dist: tqdm
